fhir_patient_summary/__init__.py
fhir_patient_summary/convertDocxToPDF.py
fhir_patient_summary/createObservationDictionary.py
fhir_patient_summary/createPatientSummaryDocument.py
fhir_patient_summary/renderTemplate.py
FHIR_Patient_Summary-0.9.6.dist-info/LICENSE
FHIR_Patient_Summary-0.9.6.dist-info/METADATA
FHIR_Patient_Summary-0.9.6.dist-info/WHEEL
FHIR_Patient_Summary-0.9.6.dist-info/top_level.txt
FHIR_Patient_Summary-0.9.6.dist-info/RECORD
