Metadata-Version: 2.1
Name: FHIR-Patient-Summary
Version: 0.9.6
Summary: Create a FHIR patient summary document in docx or pdf format.
Home-page: https://github.com/nicford/FHIR-Patient-Summary
Author: Nicolas Ford
Author-email: zcabnjf@ucl.ac.uk
License: MIT
Platform: UNKNOWN
Requires-Python: >=3.7
Requires-Dist: datetime
Requires-Dist: FHIR-Parser (==0.1.5)
Requires-Dist: docxtpl
